boxcounting/1D_random_cantor.bin
boxcounting/2D_apollonian_gasket.bin
boxcounting/3D_random_cantor.bin
boxcounting/__init__.py
boxcounting/boxcounting.py
boxcounting/runTests.py
boxcounting-1.0.0.3.dist-info/LICENSE
boxcounting-1.0.0.3.dist-info/METADATA
boxcounting-1.0.0.3.dist-info/WHEEL
boxcounting-1.0.0.3.dist-info/top_level.txt
boxcounting-1.0.0.3.dist-info/RECORD
