Metadata-Version: 2.1
Name: boxcounting
Version: 1.0.0.3
Summary: A python port of the MATLAB boxcount to calculate the     fractal (box-counting) dimension of 1D, 2D or 3D data
Home-page: https://github.com/Phoenixfire1081/fractaldimension
Author: Abhishek Harikrishnan
Author-email: abhishek.harikrishnan@fu-berlin.de
License: MIT
Platform: UNKNOWN
Requires-Python: >=3.8
License-File: LICENSE
